sqlite_utils_sqlite_vss/__init__.py
sqlite_utils_sqlite_vss/version.py
sqlite_utils_sqlite_vss-0.1.2.dist-info/METADATA
sqlite_utils_sqlite_vss-0.1.2.dist-info/WHEEL
sqlite_utils_sqlite_vss-0.1.2.dist-info/entry_points.txt
sqlite_utils_sqlite_vss-0.1.2.dist-info/top_level.txt
sqlite_utils_sqlite_vss-0.1.2.dist-info/RECORD
